kagsasrc/__init__.py
kagsasrc/__main__.py
kagsasrc/built_modules.py
kagsasrc/compiler.py
kagsasrc/errors.py
kagsasrc/exec_data.py
kagsasrc/lexer.py
kagsasrc/libtemplate.py
kagsasrc/methods.py
kagsasrc/parse_assign.py
kagsasrc/parse_cmnt.py
kagsasrc/parse_co.py
kagsasrc/parse_cparen.py
kagsasrc/parse_dot_coma.py
kagsasrc/parse_endl.py
kagsasrc/parse_id.py
kagsasrc/parse_keyword.py
kagsasrc/parse_math.py
kagsasrc/parse_number.py
kagsasrc/parse_paren.py
kagsasrc/parse_sformat.py
kagsasrc/parse_string.py
kagsasrc/parser.py
kagsasrc/paths.py
kagsasrc/syntax_checker.py
kagsa-1.2.0.dist-info/LICENSE
kagsa-1.2.0.dist-info/METADATA
kagsa-1.2.0.dist-info/WHEEL
kagsa-1.2.0.dist-info/entry_points.txt
kagsa-1.2.0.dist-info/top_level.txt
kagsa-1.2.0.dist-info/RECORD
