Metadata-Version: 2.1
Name: kagsa
Version: 1.2.0
Summary: PROGRAMMING LANGUAGE
Home-page: https://www.kagsa.org/
Author: KAGSA PROGRAMMING LANGUAGE
Author-email: admin@kagsa.org
License: MIT
Project-URL: Source, https://github.com/kagsa/kagsa
Project-URL: Report Bugs, https://github.com/kagsa/kagsa/issues
Project-URL: Download, https://pypi.org/project/kagsa/#files
Project-URL: Documentation, https://github.com/kagsa/kagsa/blob/master/README.md
Project-URL: Website, https://www.kagsa.org/
Keywords: programming,language,programming language,kagsa,lang,kg,KG,KAGSA
License-File: LICENSE
Requires-Dist: requests
Requires-Dist: sly (==0.4)
Requires-Dist: coloredlogs (==15.0.1)
Requires-Dist: colorama (==0.4.4)
Requires-Dist: keyboard (==0.13.5)
Requires-Dist: forbiddenfruit (==0.1.4)
